selenuim_leo/__init__.py
selenuim_leo/selenium_leo.py
selenuim_leo-0.1.6.dist-info/METADATA
selenuim_leo-0.1.6.dist-info/WHEEL
selenuim_leo-0.1.6.dist-info/RECORD
