Metadata-Version: 2.1
Name: selenuim-leo
Version: 0.1.6
Summary: 
Author: leomoraesguitar
Author-email: 123950901+leomoraesguitar@users.noreply.github.com
Requires-Python: >=3.11,<4.0
Classifier: Programming Language :: Python :: 3
Classifier: Programming Language :: Python :: 3.11
Classifier: Programming Language :: Python :: 3.12
Requires-Dist: auto-download-undetected-chromedriver (>=0.16,<0.17)
Requires-Dist: pyperclip (>=1.8.2,<2.0.0)
Requires-Dist: selenium (>=4.17.2,<5.0.0)
Requires-Dist: undetected-chromedriver (>=3.5.4,<4.0.0)
